ssb_libtest22/__init__.py
ssb_libtest22/__main__.py
ssb_libtest22/functions.py
ssb_libtest22/py.typed
ssb_libtest22-0.0.1.dist-info/LICENSE
ssb_libtest22-0.0.1.dist-info/METADATA
ssb_libtest22-0.0.1.dist-info/WHEEL
ssb_libtest22-0.0.1.dist-info/entry_points.txt
ssb_libtest22-0.0.1.dist-info/RECORD
