Metadata-Version: 2.1
Name: ssb-libtest22
Version: 0.0.1
Summary: SSB Libtest22
Home-page: https://github.com/statisticsnorway/ssb-libtest22
License: MIT
Author: Kristian Lønø
Author-email: krl@ssb.no
Requires-Python: >=3.9,<4.0
Classifier: Development Status :: 3 - Alpha
Classifier: License :: OSI Approved :: MIT License
Classifier: Programming Language :: Python :: 3
Classifier: Programming Language :: Python :: 3.9
Classifier: Programming Language :: Python :: 3.10
Classifier: Programming Language :: Python :: 3.11
Classifier: Programming Language :: Python :: 3.12
Requires-Dist: click (>=8.0.1)
Project-URL: Changelog, https://github.com/statisticsnorway/ssb-libtest22/releases
Project-URL: Documentation, https://statisticsnorway.github.io/ssb-libtest22
Project-URL: Repository, https://github.com/statisticsnorway/ssb-libtest22
